Modern_GUI_v3/__init__.py
Modern_GUI_v3/__main__.py
Modern_GUI_v3-1.0.dist-info/LICENCE.txt
Modern_GUI_v3-1.0.dist-info/METADATA
Modern_GUI_v3-1.0.dist-info/WHEEL
Modern_GUI_v3-1.0.dist-info/top_level.txt
Modern_GUI_v3-1.0.dist-info/RECORD
