Metadata-Version: 2.1
Name: Modern-GUI-v3
Version: 1.0
Summary: A Module to Build Modern GUI Source Files Without Internet Connection!
Home-page: https://github.com/sancho1952007/Modern-GUI-v3.0
Author: Sancho Godinho
License: UNKNOWN
Project-URL: Bug Tracker, https://github.com/sancho1952007/Modern-GUI-v3.0/issues
Keywords: build
Platform: UNKNOWN
